__init__.py
jupyformat.py
jupyformat-1.0.0.dist-info/LICENSE
jupyformat-1.0.0.dist-info/METADATA
jupyformat-1.0.0.dist-info/WHEEL
jupyformat-1.0.0.dist-info/top_level.txt
jupyformat-1.0.0.dist-info/RECORD
