Metadata-Version: 2.1
Name: jupyformat
Version: 1.0.0
Summary: Custom functions for transforming files for jupyter book
Author-email: Juan Sebastian Prieto <js.prieto10@uniandes.edu.co>
License: Apache License
Project-URL: Homepage, https://github.com/jsprieto10/pyformat
Keywords: jupyter book,jupytext,nbformat,md5,custom parser,md,markdown
Classifier: License :: OSI Approved :: Apache Software License
Classifier: Programming Language :: Python
Classifier: Programming Language :: Python :: 3
Requires-Python: >=3.8
License-File: LICENSE
Requires-Dist: jupytext
Provides-Extra: dev
Requires-Dist: black ; extra == 'dev'
Requires-Dist: bumpver ; extra == 'dev'
Requires-Dist: isort ; extra == 'dev'
Requires-Dist: pip-tools ; extra == 'dev'
Requires-Dist: pytest ; extra == 'dev'
